RsSgt/RsSgt.py
RsSgt/__init__.py
RsSgt/enums.py
RsSgt/repcap.py
RsSgt/CustomFiles/__init__.py
RsSgt/CustomFiles/arb_files.py
RsSgt/CustomFiles/digital_modulation.py
RsSgt/CustomFiles/events.py
RsSgt/CustomFiles/utilities.py
RsSgt/Implementations/Sconfiguration.py
RsSgt/Implementations/__init__.py
RsSgt/Implementations/Calibration/All.py
RsSgt/Implementations/Calibration/Frequency.py
RsSgt/Implementations/Calibration/Level.py
RsSgt/Implementations/Calibration/__init__.py
RsSgt/Implementations/Calibration/IqModulator/Bband.py
RsSgt/Implementations/Calibration/IqModulator/IqModulator.py
RsSgt/Implementations/Calibration/IqModulator/__init__.py
RsSgt/Implementations/Connector/RefLo.py
RsSgt/Implementations/Connector/__init__.py
RsSgt/Implementations/Connector/User/Omode.py
RsSgt/Implementations/Connector/User/Threshold.py
RsSgt/Implementations/Connector/User/__init__.py
RsSgt/Implementations/Connector/User/Clock/Impedance.py
RsSgt/Implementations/Connector/User/Clock/Slope.py
RsSgt/Implementations/Connector/User/Clock/__init__.py
RsSgt/Implementations/Connector/User/Trigger/Impedance.py
RsSgt/Implementations/Connector/User/Trigger/Slope.py
RsSgt/Implementations/Connector/User/Trigger/__init__.py
RsSgt/Implementations/Diagnostic/Point.py
RsSgt/Implementations/Diagnostic/__init__.py
RsSgt/Implementations/MassMemory/__init__.py
RsSgt/Implementations/MassMemory/Catalog/Length.py
RsSgt/Implementations/MassMemory/Catalog/__init__.py
RsSgt/Implementations/MassMemory/Dcatalog/Length.py
RsSgt/Implementations/MassMemory/Dcatalog/__init__.py
RsSgt/Implementations/MassMemory/Load/State.py
RsSgt/Implementations/MassMemory/Load/__init__.py
RsSgt/Implementations/MassMemory/Store/State.py
RsSgt/Implementations/MassMemory/Store/__init__.py
RsSgt/Implementations/Output/Protection.py
RsSgt/Implementations/Output/State.py
RsSgt/Implementations/Output/__init__.py
RsSgt/Implementations/Output/Afixed/Range.py
RsSgt/Implementations/Output/Afixed/__init__.py
RsSgt-5.0.232.dist-info/METADATA
RsSgt-5.0.232.dist-info/WHEEL
RsSgt-5.0.232.dist-info/top_level.txt
RsSgt-5.0.232.dist-info/RECORD
